pydantic_dydb/__init__.py
pydantic_dydb/_async_initialization.py
pydantic_dydb/_async_model.py
pydantic_dydb/_config.py
pydantic_dydb/_constants.py
pydantic_dydb/_initialization.py
pydantic_dydb/_json.py
pydantic_dydb/_model.py
pydantic_dydb-0.1.21.dist-info/LICENSE.md
pydantic_dydb-0.1.21.dist-info/WHEEL
pydantic_dydb-0.1.21.dist-info/METADATA
pydantic_dydb-0.1.21.dist-info/RECORD
